Metadata-Version: 1.0
Name: qEngineApi
Version: 0.1.3
Summary: Connect and do something with qlik engine api
Home-page: https://github.com/SemenovDaniil/qEngineApi
Author: UNKNOWN
Author-email: daniil.semenov@internet.ru
License: UNKNOWN
Platform: UNKNOWN
